nanmai_tts/__init__.py
nanmai_tts/_version.py
nanmai_tts/auth.py
nanmai_tts/communicate.py
nanmai_tts/constants.py
nanmai_tts/exceptions.py
nanmai_tts/util.py
nanmai_tts/voices.py
nanmai_tts-2025.12.30.213241.dist-info/METADATA
nanmai_tts-2025.12.30.213241.dist-info/WHEEL
nanmai_tts-2025.12.30.213241.dist-info/entry_points.txt
nanmai_tts-2025.12.30.213241.dist-info/licenses/LICENSE
nanmai_tts-2025.12.30.213241.dist-info/RECORD
