Metadata-Version: 2.4
Name: nanmai-tts
Version: 2025.12.30.213241
Summary: Async Python library for Nanmai TTS (DeepSeek/Kimi voices)
Author-email: SpeakUB Community <speakub@example.com>
Maintainer-email: SpeakUB Community <speakub@example.com>
License-Expression: MIT
License-File: LICENSE
Keywords: async,chinese,deepseek,kimi,nanmai,text-to-speech,tts
Classifier: Development Status :: 3 - Alpha
Classifier: Intended Audience :: Developers
Classifier: Operating System :: OS Independent
Classifier: Programming Language :: Python :: 3
Classifier: Programming Language :: Python :: 3.8
Classifier: Programming Language :: Python :: 3.9
Classifier: Programming Language :: Python :: 3.10
Classifier: Programming Language :: Python :: 3.11
Classifier: Programming Language :: Python :: 3.12
Classifier: Topic :: Multimedia :: Sound/Audio :: Speech
Classifier: Topic :: Software Development :: Libraries :: Python Modules
Requires-Python: >=3.8
Requires-Dist: aiohttp>=3.8.0
